{
  "header": "fielddata/script/scr_seq/event_UNION.h",
  "objects": [
    {
      "id": "obj_UNION_pcwoman3",
      "ovid": "SPRITE_PCWOMAN3",
      "mvt": 0,
      "type": 0,
      "flag": "FLAG_NOTHING",
      "scr": "_EV_scr_seq_UNION_007 + 1",
      "dirn": 1,
      "eye": 0,
      "unk10": 0,
      "tsure_poke_color": 0,
      "xrange": 0,
      "yrange": 0,
      "x": 3,
      "y": 3,
      "z": 0
    },
    {
      "id": "obj_UNION_boy1",
      "ovid": "SPRITE_BOY1",
      "mvt": 0,
      "type": 0,
      "flag": "FLAG_NOTHING",
      "scr": "_EV_scr_seq_UNION_003 + 1",
      "dirn": 1,
      "eye": 0,
      "unk10": 0,
      "tsure_poke_color": 0,
      "xrange": 0,
      "yrange": 0,
      "x": 3,
      "y": 12,
      "z": 0
    },
    {
      "id": "obj_UNION_boy1_2",
      "ovid": "SPRITE_BOY1",
      "mvt": 0,
      "type": 0,
      "flag": "FLAG_NOTHING",
      "scr": "_EV_scr_seq_UNION_003 + 1",
      "dirn": 1,
      "eye": 0,
      "unk10": 0,
      "tsure_poke_color": 0,
      "xrange": 0,
      "yrange": 0,
      "x": 11,
      "y": 9,
      "z": 0
    },
    {
      "id": "obj_UNION_boy1_3",
      "ovid": "SPRITE_BOY1",
      "mvt": 0,
      "type": 0,
      "flag": "FLAG_NOTHING",
      "scr": "_EV_scr_seq_UNION_003 + 1",
      "dirn": 1,
      "eye": 0,
      "unk10": 0,
      "tsure_poke_color": 0,
      "xrange": 0,
      "yrange": 0,
      "x": 5,
      "y": 9,
      "z": 0
    },
    {
      "id": "obj_UNION_lady",
      "ovid": "SPRITE_LADY",
      "mvt": 0,
      "type": 0,
      "flag": "FLAG_NOTHING",
      "scr": "_EV_scr_seq_UNION_003 + 1",
      "dirn": 1,
      "eye": 0,
      "unk10": 0,
      "tsure_poke_color": 0,
      "xrange": 0,
      "yrange": 0,
      "x": 14,
      "y": 6,
      "z": 0
    },
    {
      "id": "obj_UNION_badman",
      "ovid": "SPRITE_BADMAN",
      "mvt": 0,
      "type": 0,
      "flag": "FLAG_NOTHING",
      "scr": "_EV_scr_seq_UNION_003 + 1",
      "dirn": 1,
      "eye": 0,
      "unk10": 0,
      "tsure_poke_color": 0,
      "xrange": 0,
      "yrange": 0,
      "x": 6,
      "y": 4,
      "z": 0
    },
    {
      "id": "obj_UNION_boy1_4",
      "ovid": "SPRITE_BOY1",
      "mvt": 0,
      "type": 0,
      "flag": "FLAG_NOTHING",
      "scr": "_EV_scr_seq_UNION_003 + 1",
      "dirn": 1,
      "eye": 0,
      "unk10": 0,
      "tsure_poke_color": 0,
      "xrange": 0,
      "yrange": 0,
      "x": 13,
      "y": 12,
      "z": 0
    },
    {
      "id": "obj_UNION_boy1_5",
      "ovid": "SPRITE_BOY1",
      "mvt": 0,
      "type": 0,
      "flag": "FLAG_NOTHING",
      "scr": "_EV_scr_seq_UNION_003 + 1",
      "dirn": 1,
      "eye": 0,
      "unk10": 0,
      "tsure_poke_color": 0,
      "xrange": 0,
      "yrange": 0,
      "x": 2,
      "y": 6,
      "z": 0
    },
    {
      "id": "obj_UNION_girl1",
      "ovid": "SPRITE_GIRL1",
      "mvt": 0,
      "type": 0,
      "flag": "FLAG_NOTHING",
      "scr": "_EV_scr_seq_UNION_003 + 1",
      "dirn": 1,
      "eye": 0,
      "unk10": 0,
      "tsure_poke_color": 0,
      "xrange": 0,
      "yrange": 0,
      "x": 10,
      "y": 4,
      "z": 0
    },
    {
      "id": "obj_UNION_boy1_6",
      "ovid": "SPRITE_BOY1",
      "mvt": 0,
      "type": 0,
      "flag": "FLAG_NOTHING",
      "scr": "_EV_scr_seq_UNION_003 + 1",
      "dirn": 1,
      "eye": 0,
      "unk10": 0,
      "tsure_poke_color": 0,
      "xrange": 0,
      "yrange": 0,
      "x": 8,
      "y": 7,
      "z": 0
    },
    {
      "id": "obj_UNION_boy1_7",
      "ovid": "SPRITE_BOY1",
      "mvt": 0,
      "type": 0,
      "flag": "FLAG_NOTHING",
      "scr": "_EV_scr_seq_UNION_003 + 1",
      "dirn": 1,
      "eye": 0,
      "unk10": 0,
      "tsure_poke_color": 0,
      "xrange": 0,
      "yrange": 0,
      "x": 8,
      "y": 11,
      "z": 0
    },
    {
      "id": "obj_UNION_boy1_8",
      "ovid": "SPRITE_BOY1",
      "mvt": 0,
      "type": 0,
      "flag": "FLAG_NOTHING",
      "scr": "_EV_scr_seq_UNION_006 + 1",
      "dirn": 2,
      "eye": 0,
      "unk10": 0,
      "tsure_poke_color": 0,
      "xrange": 0,
      "yrange": 0,
      "x": 4,
      "y": 12,
      "z": 0
    },
    {
      "id": "obj_UNION_boy1_9",
      "ovid": "SPRITE_BOY1",
      "mvt": 0,
      "type": 0,
      "flag": "FLAG_NOTHING",
      "scr": "_EV_scr_seq_UNION_006 + 1",
      "dirn": 0,
      "eye": 0,
      "unk10": 0,
      "tsure_poke_color": 0,
      "xrange": 0,
      "yrange": 0,
      "x": 3,
      "y": 13,
      "z": 0
    },
    {
      "id": "obj_UNION_boy1_10",
      "ovid": "SPRITE_BOY1",
      "mvt": 0,
      "type": 0,
      "flag": "FLAG_NOTHING",
      "scr": "_EV_scr_seq_UNION_006 + 1",
      "dirn": 3,
      "eye": 0,
      "unk10": 0,
      "tsure_poke_color": 0,
      "xrange": 0,
      "yrange": 0,
      "x": 2,
      "y": 12,
      "z": 0
    },
    {
      "id": "obj_UNION_boy1_11",
      "ovid": "SPRITE_BOY1",
      "mvt": 0,
      "type": 0,
      "flag": "FLAG_NOTHING",
      "scr": "_EV_scr_seq_UNION_006 + 1",
      "dirn": 1,
      "eye": 0,
      "unk10": 0,
      "tsure_poke_color": 0,
      "xrange": 0,
      "yrange": 0,
      "x": 3,
      "y": 11,
      "z": 0
    },
    {
      "id": "obj_UNION_boy1_12",
      "ovid": "SPRITE_BOY1",
      "mvt": 0,
      "type": 0,
      "flag": "FLAG_NOTHING",
      "scr": "_EV_scr_seq_UNION_006 + 1",
      "dirn": 2,
      "eye": 0,
      "unk10": 0,
      "tsure_poke_color": 0,
      "xrange": 0,
      "yrange": 0,
      "x": 12,
      "y": 9,
      "z": 0
    },
    {
      "id": "obj_UNION_boy1_13",
      "ovid": "SPRITE_BOY1",
      "mvt": 0,
      "type": 0,
      "flag": "FLAG_NOTHING",
      "scr": "_EV_scr_seq_UNION_006 + 1",
      "dirn": 0,
      "eye": 0,
      "unk10": 0,
      "tsure_poke_color": 0,
      "xrange": 0,
      "yrange": 0,
      "x": 11,
      "y": 10,
      "z": 0
    },
    {
      "id": "obj_UNION_boy1_14",
      "ovid": "SPRITE_BOY1",
      "mvt": 0,
      "type": 0,
      "flag": "FLAG_NOTHING",
      "scr": "_EV_scr_seq_UNION_006 + 1",
      "dirn": 3,
      "eye": 0,
      "unk10": 0,
      "tsure_poke_color": 0,
      "xrange": 0,
      "yrange": 0,
      "x": 10,
      "y": 9,
      "z": 0
    },
    {
      "id": "obj_UNION_boy1_15",
      "ovid": "SPRITE_BOY1",
      "mvt": 0,
      "type": 0,
      "flag": "FLAG_NOTHING",
      "scr": "_EV_scr_seq_UNION_006 + 1",
      "dirn": 1,
      "eye": 0,
      "unk10": 0,
      "tsure_poke_color": 0,
      "xrange": 0,
      "yrange": 0,
      "x": 11,
      "y": 8,
      "z": 0
    },
    {
      "id": "obj_UNION_boy1_16",
      "ovid": "SPRITE_BOY1",
      "mvt": 0,
      "type": 0,
      "flag": "FLAG_NOTHING",
      "scr": "_EV_scr_seq_UNION_006 + 1",
      "dirn": 2,
      "eye": 0,
      "unk10": 0,
      "tsure_poke_color": 0,
      "xrange": 0,
      "yrange": 0,
      "x": 6,
      "y": 9,
      "z": 0
    },
    {
      "id": "obj_UNION_boy1_17",
      "ovid": "SPRITE_BOY1",
      "mvt": 0,
      "type": 0,
      "flag": "FLAG_NOTHING",
      "scr": "_EV_scr_seq_UNION_006 + 1",
      "dirn": 0,
      "eye": 0,
      "unk10": 0,
      "tsure_poke_color": 0,
      "xrange": 0,
      "yrange": 0,
      "x": 5,
      "y": 10,
      "z": 0
    },
    {
      "id": "obj_UNION_boy1_18",
      "ovid": "SPRITE_BOY1",
      "mvt": 0,
      "type": 0,
      "flag": "FLAG_NOTHING",
      "scr": "_EV_scr_seq_UNION_006 + 1",
      "dirn": 3,
      "eye": 0,
      "unk10": 0,
      "tsure_poke_color": 0,
      "xrange": 0,
      "yrange": 0,
      "x": 4,
      "y": 9,
      "z": 0
    },
    {
      "id": "obj_UNION_boy1_19",
      "ovid": "SPRITE_BOY1",
      "mvt": 0,
      "type": 0,
      "flag": "FLAG_NOTHING",
      "scr": "_EV_scr_seq_UNION_006 + 1",
      "dirn": 1,
      "eye": 0,
      "unk10": 0,
      "tsure_poke_color": 0,
      "xrange": 0,
      "yrange": 0,
      "x": 5,
      "y": 8,
      "z": 0
    },
    {
      "id": "obj_UNION_woman3",
      "ovid": "SPRITE_WOMAN3",
      "mvt": 0,
      "type": 0,
      "flag": "FLAG_NOTHING",
      "scr": "_EV_scr_seq_UNION_006 + 1",
      "dirn": 2,
      "eye": 0,
      "unk10": 0,
      "tsure_poke_color": 0,
      "xrange": 0,
      "yrange": 0,
      "x": 15,
      "y": 6,
      "z": 0
    },
    {
      "id": "obj_UNION_cowgirl",
      "ovid": "SPRITE_COWGIRL",
      "mvt": 0,
      "type": 0,
      "flag": "FLAG_NOTHING",
      "scr": "_EV_scr_seq_UNION_006 + 1",
      "dirn": 0,
      "eye": 0,
      "unk10": 0,
      "tsure_poke_color": 0,
      "xrange": 0,
      "yrange": 0,
      "x": 14,
      "y": 7,
      "z": 0
    },
    {
      "id": "obj_UNION_gorggeousw",
      "ovid": "SPRITE_GORGGEOUSW",
      "mvt": 0,
      "type": 0,
      "flag": "FLAG_NOTHING",
      "scr": "_EV_scr_seq_UNION_006 + 1",
      "dirn": 3,
      "eye": 0,
      "unk10": 0,
      "tsure_poke_color": 0,
      "xrange": 0,
      "yrange": 0,
      "x": 13,
      "y": 6,
      "z": 0
    },
    {
      "id": "obj_UNION_idol",
      "ovid": "SPRITE_IDOL",
      "mvt": 0,
      "type": 0,
      "flag": "FLAG_NOTHING",
      "scr": "_EV_scr_seq_UNION_006 + 1",
      "dirn": 1,
      "eye": 0,
      "unk10": 0,
      "tsure_poke_color": 0,
      "xrange": 0,
      "yrange": 0,
      "x": 14,
      "y": 5,
      "z": 0
    },
    {
      "id": "obj_UNION_boy3",
      "ovid": "SPRITE_BOY3",
      "mvt": 0,
      "type": 0,
      "flag": "FLAG_NOTHING",
      "scr": "_EV_scr_seq_UNION_006 + 1",
      "dirn": 2,
      "eye": 0,
      "unk10": 0,
      "tsure_poke_color": 0,
      "xrange": 0,
      "yrange": 0,
      "x": 7,
      "y": 4,
      "z": 0
    },
    {
      "id": "obj_UNION_explore",
      "ovid": "SPRITE_EXPLORE",
      "mvt": 0,
      "type": 0,
      "flag": "FLAG_NOTHING",
      "scr": "_EV_scr_seq_UNION_006 + 1",
      "dirn": 0,
      "eye": 0,
      "unk10": 0,
      "tsure_poke_color": 0,
      "xrange": 0,
      "yrange": 0,
      "x": 6,
      "y": 5,
      "z": 0
    },
    {
      "id": "obj_UNION_fighter",
      "ovid": "SPRITE_FIGHTER",
      "mvt": 0,
      "type": 0,
      "flag": "FLAG_NOTHING",
      "scr": "_EV_scr_seq_UNION_006 + 1",
      "dirn": 3,
      "eye": 0,
      "unk10": 0,
      "tsure_poke_color": 0,
      "xrange": 0,
      "yrange": 0,
      "x": 5,
      "y": 4,
      "z": 0
    },
    {
      "id": "obj_UNION_man3",
      "ovid": "SPRITE_MAN3",
      "mvt": 0,
      "type": 0,
      "flag": "FLAG_NOTHING",
      "scr": "_EV_scr_seq_UNION_006 + 1",
      "dirn": 1,
      "eye": 0,
      "unk10": 0,
      "tsure_poke_color": 0,
      "xrange": 0,
      "yrange": 0,
      "x": 6,
      "y": 3,
      "z": 0
    },
    {
      "id": "obj_UNION_boy1_20",
      "ovid": "SPRITE_BOY1",
      "mvt": 0,
      "type": 0,
      "flag": "FLAG_NOTHING",
      "scr": "_EV_scr_seq_UNION_006 + 1",
      "dirn": 2,
      "eye": 0,
      "unk10": 0,
      "tsure_poke_color": 0,
      "xrange": 0,
      "yrange": 0,
      "x": 14,
      "y": 12,
      "z": 0
    },
    {
      "id": "obj_UNION_boy1_21",
      "ovid": "SPRITE_BOY1",
      "mvt": 0,
      "type": 0,
      "flag": "FLAG_NOTHING",
      "scr": "_EV_scr_seq_UNION_006 + 1",
      "dirn": 0,
      "eye": 0,
      "unk10": 0,
      "tsure_poke_color": 0,
      "xrange": 0,
      "yrange": 0,
      "x": 13,
      "y": 13,
      "z": 0
    },
    {
      "id": "obj_UNION_boy1_22",
      "ovid": "SPRITE_BOY1",
      "mvt": 0,
      "type": 0,
      "flag": "FLAG_NOTHING",
      "scr": "_EV_scr_seq_UNION_006 + 1",
      "dirn": 3,
      "eye": 0,
      "unk10": 0,
      "tsure_poke_color": 0,
      "xrange": 0,
      "yrange": 0,
      "x": 12,
      "y": 12,
      "z": 0
    },
    {
      "id": "obj_UNION_boy1_23",
      "ovid": "SPRITE_BOY1",
      "mvt": 0,
      "type": 0,
      "flag": "FLAG_NOTHING",
      "scr": "_EV_scr_seq_UNION_006 + 1",
      "dirn": 1,
      "eye": 0,
      "unk10": 0,
      "tsure_poke_color": 0,
      "xrange": 0,
      "yrange": 0,
      "x": 13,
      "y": 11,
      "z": 0
    },
    {
      "id": "obj_UNION_boy1_24",
      "ovid": "SPRITE_BOY1",
      "mvt": 0,
      "type": 0,
      "flag": "FLAG_NOTHING",
      "scr": "_EV_scr_seq_UNION_006 + 1",
      "dirn": 2,
      "eye": 0,
      "unk10": 0,
      "tsure_poke_color": 0,
      "xrange": 0,
      "yrange": 0,
      "x": 3,
      "y": 6,
      "z": 0
    },
    {
      "id": "obj_UNION_boy1_25",
      "ovid": "SPRITE_BOY1",
      "mvt": 0,
      "type": 0,
      "flag": "FLAG_NOTHING",
      "scr": "_EV_scr_seq_UNION_006 + 1",
      "dirn": 0,
      "eye": 0,
      "unk10": 0,
      "tsure_poke_color": 0,
      "xrange": 0,
      "yrange": 0,
      "x": 2,
      "y": 7,
      "z": 0
    },
    {
      "id": "obj_UNION_boy1_26",
      "ovid": "SPRITE_BOY1",
      "mvt": 0,
      "type": 0,
      "flag": "FLAG_NOTHING",
      "scr": "_EV_scr_seq_UNION_006 + 1",
      "dirn": 3,
      "eye": 0,
      "unk10": 0,
      "tsure_poke_color": 0,
      "xrange": 0,
      "yrange": 0,
      "x": 1,
      "y": 6,
      "z": 0
    },
    {
      "id": "obj_UNION_boy1_27",
      "ovid": "SPRITE_BOY1",
      "mvt": 0,
      "type": 0,
      "flag": "FLAG_NOTHING",
      "scr": "_EV_scr_seq_UNION_006 + 1",
      "dirn": 1,
      "eye": 0,
      "unk10": 0,
      "tsure_poke_color": 0,
      "xrange": 0,
      "yrange": 0,
      "x": 2,
      "y": 5,
      "z": 0
    },
    {
      "id": "obj_UNION_gorggeousm",
      "ovid": "SPRITE_GORGGEOUSM",
      "mvt": 0,
      "type": 0,
      "flag": "FLAG_NOTHING",
      "scr": "_EV_scr_seq_UNION_006 + 1",
      "dirn": 2,
      "eye": 0,
      "unk10": 0,
      "tsure_poke_color": 0,
      "xrange": 0,
      "yrange": 0,
      "x": 11,
      "y": 4,
      "z": 0
    },
    {
      "id": "obj_UNION_girl2",
      "ovid": "SPRITE_GIRL2",
      "mvt": 0,
      "type": 0,
      "flag": "FLAG_NOTHING",
      "scr": "_EV_scr_seq_UNION_006 + 1",
      "dirn": 0,
      "eye": 0,
      "unk10": 0,
      "tsure_poke_color": 0,
      "xrange": 0,
      "yrange": 0,
      "x": 10,
      "y": 5,
      "z": 0
    },
    {
      "id": "obj_UNION_woman2",
      "ovid": "SPRITE_WOMAN2",
      "mvt": 0,
      "type": 0,
      "flag": "FLAG_NOTHING",
      "scr": "_EV_scr_seq_UNION_006 + 1",
      "dirn": 3,
      "eye": 0,
      "unk10": 0,
      "tsure_poke_color": 0,
      "xrange": 0,
      "yrange": 0,
      "x": 9,
      "y": 4,
      "z": 0
    },
    {
      "id": "obj_UNION_mystery",
      "ovid": "SPRITE_MYSTERY",
      "mvt": 0,
      "type": 0,
      "flag": "FLAG_NOTHING",
      "scr": "_EV_scr_seq_UNION_006 + 1",
      "dirn": 1,
      "eye": 0,
      "unk10": 0,
      "tsure_poke_color": 0,
      "xrange": 0,
      "yrange": 0,
      "x": 10,
      "y": 3,
      "z": 0
    },
    {
      "id": "obj_UNION_boy1_28",
      "ovid": "SPRITE_BOY1",
      "mvt": 0,
      "type": 0,
      "flag": "FLAG_NOTHING",
      "scr": "_EV_scr_seq_UNION_006 + 1",
      "dirn": 2,
      "eye": 0,
      "unk10": 0,
      "tsure_poke_color": 0,
      "xrange": 0,
      "yrange": 0,
      "x": 9,
      "y": 7,
      "z": 0
    },
    {
      "id": "obj_UNION_boy1_29",
      "ovid": "SPRITE_BOY1",
      "mvt": 0,
      "type": 0,
      "flag": "FLAG_NOTHING",
      "scr": "_EV_scr_seq_UNION_006 + 1",
      "dirn": 0,
      "eye": 0,
      "unk10": 0,
      "tsure_poke_color": 0,
      "xrange": 0,
      "yrange": 0,
      "x": 8,
      "y": 8,
      "z": 0
    },
    {
      "id": "obj_UNION_boy1_30",
      "ovid": "SPRITE_BOY1",
      "mvt": 0,
      "type": 0,
      "flag": "FLAG_NOTHING",
      "scr": "_EV_scr_seq_UNION_006 + 1",
      "dirn": 3,
      "eye": 0,
      "unk10": 0,
      "tsure_poke_color": 0,
      "xrange": 0,
      "yrange": 0,
      "x": 7,
      "y": 7,
      "z": 0
    },
    {
      "id": "obj_UNION_boy1_31",
      "ovid": "SPRITE_BOY1",
      "mvt": 0,
      "type": 0,
      "flag": "FLAG_NOTHING",
      "scr": "_EV_scr_seq_UNION_006 + 1",
      "dirn": 1,
      "eye": 0,
      "unk10": 0,
      "tsure_poke_color": 0,
      "xrange": 0,
      "yrange": 0,
      "x": 8,
      "y": 6,
      "z": 0
    },
    {
      "id": "obj_UNION_boy1_32",
      "ovid": "SPRITE_BOY1",
      "mvt": 0,
      "type": 0,
      "flag": "FLAG_NOTHING",
      "scr": "_EV_scr_seq_UNION_006 + 1",
      "dirn": 2,
      "eye": 0,
      "unk10": 0,
      "tsure_poke_color": 0,
      "xrange": 0,
      "yrange": 0,
      "x": 9,
      "y": 11,
      "z": 0
    },
    {
      "id": "obj_UNION_boy1_33",
      "ovid": "SPRITE_BOY1",
      "mvt": 0,
      "type": 0,
      "flag": "FLAG_NOTHING",
      "scr": "_EV_scr_seq_UNION_006 + 1",
      "dirn": 0,
      "eye": 0,
      "unk10": 0,
      "tsure_poke_color": 0,
      "xrange": 0,
      "yrange": 0,
      "x": 8,
      "y": 12,
      "z": 0
    },
    {
      "id": "obj_UNION_boy1_34",
      "ovid": "SPRITE_BOY1",
      "mvt": 0,
      "type": 0,
      "flag": "FLAG_NOTHING",
      "scr": "_EV_scr_seq_UNION_006 + 1",
      "dirn": 3,
      "eye": 0,
      "unk10": 0,
      "tsure_poke_color": 0,
      "xrange": 0,
      "yrange": 0,
      "x": 7,
      "y": 11,
      "z": 0
    },
    {
      "id": "obj_UNION_boy1_35",
      "ovid": "SPRITE_BOY1",
      "mvt": 0,
      "type": 0,
      "flag": "FLAG_NOTHING",
      "scr": "_EV_scr_seq_UNION_006 + 1",
      "dirn": 1,
      "eye": 0,
      "unk10": 0,
      "tsure_poke_color": 0,
      "xrange": 0,
      "yrange": 0,
      "x": 8,
      "y": 10,
      "z": 0
    }
  ],
  "warps": [
    {
      "x": 8,
      "y": 14,
      "header": "MAP_T27PC0101",
      "anchor": 1,
      "height": 0
    }
  ]
}