{
  "header": "fielddata/script/scr_seq/event_R03.h",
  "bgs": [
    {
      "scr": "_EV_scr_seq_R03_000 + 1",
      "type": 1,
      "x": 1168,
      "y": 121,
      "z": 0,
      "dir": 4
    },
    {
      "scr": "std_hiddenitem_r03_star_piece_2",
      "type": 2,
      "x": 1095,
      "y": 121,
      "z": 0,
      "dir": 4
    },
    {
      "scr": "std_hiddenitem_r03_star_piece",
      "type": 2,
      "x": 1100,
      "y": 116,
      "z": 0,
      "dir": 4
    },
    {
      "scr": "std_hiddenitem_r03_hyper_potion",
      "type": 2,
      "x": 1160,
      "y": 105,
      "z": 0,
      "dir": 4
    },
    {
      "scr": "_EV_scr_seq_R03_004 + 1",
      "type": 0,
      "x": 1093,
      "y": 115,
      "z": 0,
      "dir": 4
    },
    {
      "scr": "_EV_scr_seq_R03_002 + 1",
      "type": 0,
      "x": 1094,
      "y": 121,
      "z": 0,
      "dir": 4
    },
    {
      "scr": "_EV_scr_seq_R03_003 + 1",
      "type": 0,
      "x": 1102,
      "y": 115,
      "z": 0,
      "dir": 4
    },
    {
      "scr": "_EV_scr_seq_R03_001 + 1",
      "type": 0,
      "x": 1100,
      "y": 122,
      "z": 0,
      "dir": 4
    }
  ],
  "objects": [
    {
      "id": "obj_R03_gsboy2",
      "sprite_id": "SPRITE_GSBOY2",
      "movement": 0,
      "type": 1,
      "flag": "FLAG_NOTHING",
      "scr": "std_trainer(TRAINER_YOUNGSTER_WARREN)",
      "dirn": 2,
      "eye": 4,
      "unk10": 0,
      "tsure_poke_color": 0,
      "xrange": 0,
      "yrange": 0,
      "x": 1110,
      "y": 99,
      "z": 0
    },
    {
      "id": "obj_R03_fire",
      "sprite_id": "SPRITE_FIRE",
      "movement": 0,
      "type": 1,
      "flag": "FLAG_NOTHING",
      "scr": "std_trainer(TRAINER_FIREBREATHER_OTIS)",
      "dirn": 0,
      "eye": 4,
      "unk10": 0,
      "tsure_poke_color": 0,
      "xrange": 0,
      "yrange": 0,
      "x": 1122,
      "y": 111,
      "z": 0
    },
    {
      "id": "obj_R03_gsboy2_2",
      "sprite_id": "SPRITE_GSBOY2",
      "movement": 0,
      "type": 1,
      "flag": "FLAG_NOTHING",
      "scr": "std_trainer(TRAINER_YOUNGSTER_JIMMY)",
      "dirn": 2,
      "eye": 4,
      "unk10": 0,
      "tsure_poke_color": 0,
      "xrange": 0,
      "yrange": 0,
      "x": 1114,
      "y": 98,
      "z": 0
    },
    {
      "id": "obj_R03_gsman3",
      "sprite_id": "SPRITE_GSMAN3",
      "movement": 0,
      "type": 1,
      "flag": "FLAG_NOTHING",
      "scr": "std_trainer(TRAINER_DOUBLE_TEAM_ZAC_AND_JEN)",
      "dirn": 1,
      "eye": 3,
      "unk10": 0,
      "tsure_poke_color": 0,
      "xrange": 0,
      "yrange": 0,
      "x": 1104,
      "y": 107,
      "z": 0
    },
    {
      "id": "obj_R03_gswoman3",
      "sprite_id": "SPRITE_GSWOMAN3",
      "movement": 0,
      "type": 1,
      "flag": "FLAG_NOTHING",
      "scr": "std_trainer_2(TRAINER_DOUBLE_TEAM_ZAC_AND_JEN)",
      "dirn": 1,
      "eye": 3,
      "unk10": 0,
      "tsure_poke_color": 0,
      "xrange": 0,
      "yrange": 0,
      "x": 1105,
      "y": 107,
      "z": 0
    },
    {
      "id": "obj_R03_fire_2",
      "sprite_id": "SPRITE_FIRE",
      "movement": 18,
      "type": 1,
      "flag": "FLAG_NOTHING",
      "scr": "std_trainer(TRAINER_FIREBREATHER_BURT)",
      "dirn": 1,
      "eye": 3,
      "unk10": 0,
      "tsure_poke_color": 0,
      "xrange": 0,
      "yrange": 0,
      "x": 1165,
      "y": 114,
      "z": 0
    },
    {
      "id": "obj_R03_mount_2",
      "sprite_id": "SPRITE_MOUNT_2",
      "movement": 8,
      "type": 1,
      "flag": "FLAG_NOTHING",
      "scr": "std_trainer(TRAINER_HIKER_BRUCE)",
      "dirn": 1,
      "eye": 4,
      "unk10": 0,
      "tsure_poke_color": 0,
      "xrange": 0,
      "yrange": 0,
      "x": 1134,
      "y": 113,
      "z": 0
    },
    {
      "id": "obj_R03_gsfighter",
      "sprite_id": "SPRITE_GSFIGHTER",
      "movement": 0,
      "type": 1,
      "flag": "FLAG_NOTHING",
      "scr": "std_trainer(TRAINER_BLACK_BELT_MANFORD)",
      "dirn": 3,
      "eye": 5,
      "unk10": 0,
      "tsure_poke_color": 0,
      "xrange": 0,
      "yrange": 0,
      "x": 1143,
      "y": 118,
      "z": 0
    },
    {
      "id": "obj_R03_gsfighter_2",
      "sprite_id": "SPRITE_GSFIGHTER",
      "movement": 0,
      "type": 1,
      "flag": "FLAG_NOTHING",
      "scr": "std_trainer(TRAINER_BLACK_BELT_ANDER)",
      "dirn": 0,
      "eye": 4,
      "unk10": 0,
      "tsure_poke_color": 0,
      "xrange": 0,
      "yrange": 0,
      "x": 1158,
      "y": 123,
      "z": 0
    },
    {
      "id": "obj_R03_mount_2_2",
      "sprite_id": "SPRITE_MOUNT_2",
      "movement": 0,
      "type": 1,
      "flag": "FLAG_NOTHING",
      "scr": "std_trainer(TRAINER_HIKER_DWIGHT)",
      "dirn": 2,
      "eye": 5,
      "unk10": 0,
      "tsure_poke_color": 0,
      "xrange": 0,
      "yrange": 0,
      "x": 1164,
      "y": 124,
      "z": 0
    },
    {
      "id": "obj_R03_gsboy2_3",
      "sprite_id": "SPRITE_GSBOY2",
      "movement": 0,
      "type": 1,
      "flag": "FLAG_NOTHING",
      "scr": "std_trainer(TRAINER_YOUNGSTER_REGIS)",
      "dirn": 2,
      "eye": 6,
      "unk10": 0,
      "tsure_poke_color": 0,
      "xrange": 0,
      "yrange": 0,
      "x": 1103,
      "y": 103,
      "z": 0
    },
    {
      "id": "obj_R03_monstarball",
      "sprite_id": "SPRITE_MONSTARBALL",
      "movement": 0,
      "type": 0,
      "flag": "FLAG_HIDE_ITEMBALL_R03_BIG_ROOT",
      "scr": "std_itemball_r03_big_root",
      "dirn": 0,
      "eye": 0,
      "unk10": 0,
      "tsure_poke_color": 0,
      "xrange": 0,
      "yrange": 0,
      "x": 1132,
      "y": 120,
      "z": 0
    },
    {
      "id": "obj_R03_breakrock",
      "sprite_id": "SPRITE_BREAKROCK",
      "movement": 0,
      "type": 0,
      "flag": "FLAG_MAPTEMP_010",
      "scr": "std_field_rock_smash",
      "dirn": 0,
      "eye": 0,
      "unk10": 0,
      "tsure_poke_color": 0,
      "xrange": 0,
      "yrange": 0,
      "x": 1161,
      "y": 105,
      "z": 0
    },
    {
      "id": "obj_R03_breakrock_2",
      "sprite_id": "SPRITE_BREAKROCK",
      "movement": 0,
      "type": 0,
      "flag": "FLAG_MAPTEMP_011",
      "scr": "std_field_rock_smash",
      "dirn": 0,
      "eye": 0,
      "unk10": 0,
      "tsure_poke_color": 0,
      "xrange": 0,
      "yrange": 0,
      "x": 1160,
      "y": 104,
      "z": 0
    },
    {
      "id": "obj_R03_breakrock_3",
      "sprite_id": "SPRITE_BREAKROCK",
      "movement": 0,
      "type": 0,
      "flag": "FLAG_MAPTEMP_012",
      "scr": "std_field_rock_smash",
      "dirn": 0,
      "eye": 0,
      "unk10": 0,
      "tsure_poke_color": 0,
      "xrange": 0,
      "yrange": 0,
      "x": 1164,
      "y": 103,
      "z": 0
    },
    {
      "id": "obj_R03_breakrock_4",
      "sprite_id": "SPRITE_BREAKROCK",
      "movement": 0,
      "type": 0,
      "flag": "FLAG_MAPTEMP_013",
      "scr": "std_field_rock_smash",
      "dirn": 0,
      "eye": 0,
      "unk10": 0,
      "tsure_poke_color": 0,
      "xrange": 0,
      "yrange": 0,
      "x": 1162,
      "y": 109,
      "z": 0
    },
    {
      "id": "obj_R03_breakrock_5",
      "sprite_id": "SPRITE_BREAKROCK",
      "movement": 0,
      "type": 0,
      "flag": "FLAG_MAPTEMP_014",
      "scr": "std_field_rock_smash",
      "dirn": 0,
      "eye": 0,
      "unk10": 0,
      "tsure_poke_color": 0,
      "xrange": 0,
      "yrange": 0,
      "x": 1160,
      "y": 113,
      "z": 0
    },
    {
      "id": "obj_R03_breakrock_6",
      "sprite_id": "SPRITE_BREAKROCK",
      "movement": 0,
      "type": 0,
      "flag": "FLAG_MAPTEMP_015",
      "scr": "std_field_rock_smash",
      "dirn": 0,
      "eye": 0,
      "unk10": 0,
      "tsure_poke_color": 0,
      "xrange": 0,
      "yrange": 0,
      "x": 1174,
      "y": 113,
      "z": 0
    },
    {
      "id": "obj_R03_breakrock_7",
      "sprite_id": "SPRITE_BREAKROCK",
      "movement": 0,
      "type": 0,
      "flag": "FLAG_MAPTEMP_016",
      "scr": "std_field_rock_smash",
      "dirn": 0,
      "eye": 0,
      "unk10": 0,
      "tsure_poke_color": 0,
      "xrange": 0,
      "yrange": 0,
      "x": 1171,
      "y": 113,
      "z": 0
    }
  ],
  "warps": [
    {
      "x": 1172,
      "y": 102,
      "header": "MAP_D02R0101",
      "anchor": 0,
      "height": 0
    },
    {
      "x": 1167,
      "y": 106,
      "header": "MAP_R03PC0101",
      "anchor": 0,
      "height": 0
    }
  ]
}