{
  "header": "fielddata/script/scr_seq/event_R09.h",
  "bgs": [
    {
      "scr": "_EV_scr_seq_R09_000 + 1",
      "type": 1,
      "x": 1367,
      "y": 143,
      "z": 0,
      "dir": 4
    },
    {
      "scr": "std_hiddenitem_r09_ether",
      "type": 2,
      "x": 1422,
      "y": 140,
      "z": 0,
      "dir": 4
    }
  ],
  "objects": [
    {
      "id": "obj_R09_campboy_2",
      "sprite_id": "SPRITE_CAMPBOY_2",
      "movement": 0,
      "type": 1,
      "flag": "FLAG_NOTHING",
      "scr": "std_trainer(TRAINER_CAMPER_SID)",
      "dirn": 3,
      "eye": 3,
      "unk10": 0,
      "tsure_poke_color": 0,
      "xrange": 0,
      "yrange": 0,
      "x": 1355,
      "y": 140,
      "z": 0
    },
    {
      "id": "obj_R09_picnicgirl_2",
      "sprite_id": "SPRITE_PICNICGIRL_2",
      "movement": 0,
      "type": 1,
      "flag": "FLAG_NOTHING",
      "scr": "std_trainer(TRAINER_PICNICKER_EDNA)",
      "dirn": 0,
      "eye": 2,
      "unk10": 0,
      "tsure_poke_color": 0,
      "xrange": 0,
      "yrange": 0,
      "x": 1361,
      "y": 155,
      "z": 0
    },
    {
      "id": "obj_R09_campboy_2_2",
      "sprite_id": "SPRITE_CAMPBOY_2",
      "movement": 0,
      "type": 1,
      "flag": "FLAG_NOTHING",
      "scr": "std_trainer(TRAINER_CAMPER_DEAN)",
      "dirn": 2,
      "eye": 5,
      "unk10": 0,
      "tsure_poke_color": 0,
      "xrange": 0,
      "yrange": 0,
      "x": 1387,
      "y": 150,
      "z": 0
    },
    {
      "id": "obj_R09_mount_2",
      "sprite_id": "SPRITE_MOUNT_2",
      "movement": 0,
      "type": 1,
      "flag": "FLAG_NOTHING",
      "scr": "std_trainer(TRAINER_HIKER_CLARKE)",
      "dirn": 1,
      "eye": 2,
      "unk10": 0,
      "tsure_poke_color": 0,
      "xrange": 0,
      "yrange": 0,
      "x": 1410,
      "y": 153,
      "z": 0
    },
    {
      "id": "obj_R09_mount_2_2",
      "sprite_id": "SPRITE_MOUNT_2",
      "movement": 5,
      "type": 1,
      "flag": "FLAG_NOTHING",
      "scr": "std_trainer(TRAINER_HIKER_EOIN)",
      "dirn": 2,
      "eye": 5,
      "unk10": 0,
      "tsure_poke_color": 0,
      "xrange": 0,
      "yrange": 0,
      "x": 1402,
      "y": 137,
      "z": 0
    },
    {
      "id": "obj_R09_picnicgirl_2_2",
      "sprite_id": "SPRITE_PICNICGIRL_2",
      "movement": 0,
      "type": 1,
      "flag": "FLAG_NOTHING",
      "scr": "std_trainer(TRAINER_PICNICKER_HEIDI)",
      "dirn": 3,
      "eye": 4,
      "unk10": 0,
      "tsure_poke_color": 0,
      "xrange": 0,
      "yrange": 0,
      "x": 1412,
      "y": 144,
      "z": 0
    },
    {
      "id": "obj_R09_tree",
      "sprite_id": "SPRITE_TREE",
      "movement": 0,
      "type": 0,
      "flag": "FLAG_MAPTEMP_010",
      "scr": "std_field_cut",
      "dirn": 0,
      "eye": 0,
      "unk10": 0,
      "tsure_poke_color": 0,
      "xrange": 0,
      "yrange": 0,
      "x": 1422,
      "y": 148,
      "z": 0
    },
    {
      "id": "obj_R09_tree_2",
      "sprite_id": "SPRITE_TREE",
      "movement": 0,
      "type": 0,
      "flag": "FLAG_MAPTEMP_011",
      "scr": "std_field_cut",
      "dirn": 0,
      "eye": 0,
      "unk10": 0,
      "tsure_poke_color": 0,
      "xrange": 0,
      "yrange": 0,
      "x": 1424,
      "y": 148,
      "z": 0
    },
    {
      "id": "obj_R09_tree_3",
      "sprite_id": "SPRITE_TREE",
      "movement": 0,
      "type": 0,
      "flag": "FLAG_MAPTEMP_012",
      "scr": "std_field_cut",
      "dirn": 0,
      "eye": 0,
      "unk10": 0,
      "tsure_poke_color": 0,
      "xrange": 0,
      "yrange": 0,
      "x": 1426,
      "y": 148,
      "z": 0
    },
    {
      "id": "obj_R09_tree_4",
      "sprite_id": "SPRITE_TREE",
      "movement": 0,
      "type": 0,
      "flag": "FLAG_MAPTEMP_013",
      "scr": "std_field_cut",
      "dirn": 0,
      "eye": 0,
      "unk10": 0,
      "tsure_poke_color": 0,
      "xrange": 0,
      "yrange": 0,
      "x": 1428,
      "y": 148,
      "z": 0
    },
    {
      "id": "obj_R09_tree_5",
      "sprite_id": "SPRITE_TREE",
      "movement": 0,
      "type": 0,
      "flag": "FLAG_MAPTEMP_014",
      "scr": "std_field_cut",
      "dirn": 0,
      "eye": 0,
      "unk10": 0,
      "tsure_poke_color": 0,
      "xrange": 0,
      "yrange": 0,
      "x": 1408,
      "y": 134,
      "z": 0
    },
    {
      "id": "obj_R09_tree_6",
      "sprite_id": "SPRITE_TREE",
      "movement": 0,
      "type": 0,
      "flag": "FLAG_MAPTEMP_015",
      "scr": "std_field_cut",
      "dirn": 0,
      "eye": 0,
      "unk10": 0,
      "tsure_poke_color": 0,
      "xrange": 0,
      "yrange": 0,
      "x": 1382,
      "y": 141,
      "z": 0
    },
    {
      "id": "obj_R09_tree_7",
      "sprite_id": "SPRITE_TREE",
      "movement": 0,
      "type": 0,
      "flag": "FLAG_MAPTEMP_016",
      "scr": "std_field_cut",
      "dirn": 0,
      "eye": 0,
      "unk10": 0,
      "tsure_poke_color": 0,
      "xrange": 0,
      "yrange": 0,
      "x": 1416,
      "y": 148,
      "z": 0
    },
    {
      "id": "obj_R09_monstarball",
      "sprite_id": "SPRITE_MONSTARBALL",
      "movement": 0,
      "type": 0,
      "flag": "FLAG_HIDE_ITEMBALL_R09_TM91",
      "scr": "std_itemball_r09_tm91",
      "dirn": 0,
      "eye": 0,
      "unk10": 0,
      "tsure_poke_color": 0,
      "xrange": 0,
      "yrange": 0,
      "x": 1415,
      "y": 136,
      "z": 0
    },
    {
      "id": "obj_R09_monstarball_2",
      "sprite_id": "SPRITE_MONSTARBALL",
      "movement": 0,
      "type": 0,
      "flag": "FLAG_HIDE_ITEMBALL_R09_FULL_RESTORE",
      "scr": "std_itemball_r09_full_restore",
      "dirn": 0,
      "eye": 0,
      "unk10": 0,
      "tsure_poke_color": 0,
      "xrange": 0,
      "yrange": 0,
      "x": 1413,
      "y": 154,
      "z": 0
    },
    {
      "id": "obj_R09_monstarball_3",
      "sprite_id": "SPRITE_MONSTARBALL",
      "movement": 0,
      "type": 0,
      "flag": "FLAG_HIDE_ITEMBALL_R09_LIGHT_CLAY",
      "scr": "std_itemball_r09_light_clay",
      "dirn": 0,
      "eye": 0,
      "unk10": 0,
      "tsure_poke_color": 0,
      "xrange": 0,
      "yrange": 0,
      "x": 1376,
      "y": 143,
      "z": 0
    },
    {
      "id": "obj_R09_monstarball_4",
      "sprite_id": "SPRITE_MONSTARBALL",
      "movement": 0,
      "type": 0,
      "flag": "FLAG_HIDE_ITEMBALL_R09_MAX_POTION",
      "scr": "std_itemball_r09_max_potion",
      "dirn": 0,
      "eye": 0,
      "unk10": 0,
      "tsure_poke_color": 0,
      "xrange": 0,
      "yrange": 0,
      "x": 1356,
      "y": 154,
      "z": 0
    }
  ]
}