{
  "header": "fielddata/script/scr_seq/event_R42.h",
  "bgs": [
    {
      "scriptId": "_EV_scr_seq_R42_002 + 1",
      "type": 1,
      "x": 427,
      "z": 177,
      "y": 0,
      "dir": 4
    },
    {
      "scriptId": "_EV_scr_seq_R42_003 + 1",
      "type": 1,
      "x": 432,
      "z": 171,
      "y": 0,
      "dir": 4
    },
    {
      "scriptId": "_EV_scr_seq_R42_004 + 1",
      "type": 1,
      "x": 491,
      "z": 172,
      "y": 0,
      "dir": 4
    },
    {
      "scriptId": "_EV_scr_seq_R42_005 + 1",
      "type": 1,
      "x": 504,
      "z": 172,
      "y": 0,
      "dir": 4
    },
    {
      "scriptId": "std_hiddenitem_r42_max_potion",
      "type": 2,
      "x": 480,
      "z": 182,
      "y": 0,
      "dir": 4
    }
  ],
  "objects": [
    {
      "id": "obj_R42_fishing_2",
      "spriteId": "SPRITE_FISHING_2",
      "movement": 15,
      "type": 1,
      "eventFlag": "FLAG_NOTHING",
      "scriptId": "std_trainer(TRAINER_FISHERMAN_TULLY)",
      "facingDirection": 1,
      "param0": 3,
      "param1": 0,
      "param2": 0,
      "xRange": 0,
      "yRange": 0,
      "x": 483,
      "z": 175,
      "y": 0
    },
    {
      "id": "obj_R42_mania",
      "spriteId": "SPRITE_MANIA",
      "movement": 15,
      "type": 1,
      "eventFlag": "FLAG_NOTHING",
      "scriptId": "std_trainer(TRAINER_POKE_MANIAC_SHANE)",
      "facingDirection": 1,
      "param0": 5,
      "param1": 0,
      "param2": 0,
      "xRange": 0,
      "yRange": 0,
      "x": 495,
      "z": 172,
      "y": 0
    },
    {
      "id": "obj_R42_mount_2",
      "spriteId": "SPRITE_MOUNT_2",
      "movement": 6,
      "type": 1,
      "eventFlag": "FLAG_NOTHING",
      "scriptId": "std_trainer(TRAINER_HIKER_BENJAMIN)",
      "facingDirection": 2,
      "param0": 5,
      "param1": 0,
      "param2": 0,
      "xRange": 0,
      "yRange": 0,
      "x": 501,
      "z": 177,
      "y": 0
    },
    {
      "id": "obj_R42_bonguri",
      "spriteId": "SPRITE_BONGURI",
      "movement": 0,
      "type": 0,
      "eventFlag": "FLAG_NOTHING",
      "scriptId": "std_apricorn_tree",
      "facingDirection": 0,
      "param0": 18,
      "param1": 0,
      "param2": 0,
      "xRange": 0,
      "yRange": 0,
      "x": 464,
      "z": 184,
      "y": 0
    },
    {
      "id": "obj_R42_bonguri_2",
      "spriteId": "SPRITE_BONGURI",
      "movement": 0,
      "type": 0,
      "eventFlag": "FLAG_NOTHING",
      "scriptId": "std_apricorn_tree",
      "facingDirection": 0,
      "param0": 19,
      "param1": 0,
      "param2": 0,
      "xRange": 0,
      "yRange": 0,
      "x": 465,
      "z": 184,
      "y": 0
    },
    {
      "id": "obj_R42_bonguri_3",
      "spriteId": "SPRITE_BONGURI",
      "movement": 0,
      "type": 0,
      "eventFlag": "FLAG_NOTHING",
      "scriptId": "std_apricorn_tree",
      "facingDirection": 0,
      "param0": 20,
      "param1": 0,
      "param2": 0,
      "xRange": 0,
      "yRange": 0,
      "x": 466,
      "z": 184,
      "y": 0
    },
    {
      "id": "obj_R42_monstarball",
      "spriteId": "SPRITE_MONSTARBALL",
      "movement": 0,
      "type": 0,
      "eventFlag": "FLAG_HIDE_ITEMBALL_R42_SUPER_POTION",
      "scriptId": "std_itemball_r42_super_potion",
      "facingDirection": 0,
      "param0": 0,
      "param1": 0,
      "param2": 0,
      "xRange": 0,
      "yRange": 0,
      "x": 472,
      "z": 176,
      "y": 0
    },
    {
      "id": "obj_R42_monstarball_2",
      "spriteId": "SPRITE_MONSTARBALL",
      "movement": 0,
      "type": 0,
      "eventFlag": "FLAG_HIDE_ITEMBALL_R42_DUBIOUS_DISC",
      "scriptId": "std_itemball_r42_dubious_disc",
      "facingDirection": 0,
      "param0": 0,
      "param1": 0,
      "param2": 0,
      "xRange": 0,
      "yRange": 0,
      "x": 477,
      "z": 166,
      "y": 0
    },
    {
      "id": "obj_R42_monstarball_3",
      "spriteId": "SPRITE_MONSTARBALL",
      "movement": 0,
      "type": 0,
      "eventFlag": "FLAG_HIDE_ITEMBALL_R42_TM65",
      "scriptId": "std_itemball_r42_tm65",
      "facingDirection": 0,
      "param0": 0,
      "param1": 0,
      "param2": 0,
      "xRange": 0,
      "yRange": 0,
      "x": 430,
      "z": 169,
      "y": 0
    },
    {
      "id": "obj_R42_tree",
      "spriteId": "SPRITE_TREE",
      "movement": 0,
      "type": 0,
      "eventFlag": "FLAG_MAPTEMP_010",
      "scriptId": "std_field_cut",
      "facingDirection": 0,
      "param0": 0,
      "param1": 0,
      "param2": 0,
      "xRange": 0,
      "yRange": 0,
      "x": 460,
      "z": 181,
      "y": 0
    },
    {
      "id": "obj_R42_mount_2_2",
      "spriteId": "SPRITE_MOUNT_2",
      "movement": 0,
      "type": 0,
      "eventFlag": "FLAG_HIDE_ROUTE_42_HIKER",
      "scriptId": 0,
      "facingDirection": 1,
      "param0": 0,
      "param1": 0,
      "param2": 0,
      "xRange": 0,
      "yRange": 0,
      "x": 436,
      "z": 171,
      "y": 0
    },
    {
      "id": "obj_R42_tsure_poke_static_suicune",
      "spriteId": "SPRITE_FOLLOWER_MON_STATIC_SUICUNE",
      "movement": 0,
      "type": 0,
      "eventFlag": "FLAG_HIDE_ROUTE_42_SUICUNE",
      "scriptId": 0,
      "facingDirection": 2,
      "param0": 0,
      "param1": 0,
      "param2": 0,
      "xRange": 0,
      "yRange": 0,
      "x": 466,
      "z": 182,
      "y": 0
    },
    {
      "id": "obj_R42_minaki",
      "spriteId": "SPRITE_MINAKI",
      "movement": 0,
      "type": 0,
      "eventFlag": "FLAG_HIDE_ROUTE_42_EUSINE",
      "scriptId": 0,
      "facingDirection": 0,
      "param0": 0,
      "param1": 0,
      "param2": 0,
      "xRange": 0,
      "yRange": 0,
      "x": 452,
      "z": 181,
      "y": 0
    }
  ],
  "warps": [
    {
      "x": 422,
      "z": 175,
      "header": "MAP_ROUTE_42_ECRUTEAK_GATEHOUSE",
      "anchor": 1,
      "y": 0
    },
    {
      "x": 422,
      "z": 176,
      "header": "MAP_ROUTE_42_ECRUTEAK_GATEHOUSE",
      "anchor": 1,
      "y": 0
    },
    {
      "x": 436,
      "z": 171,
      "header": "MAP_MOUNT_MORTAR_1F_ENTRANCE",
      "anchor": 0,
      "y": 0
    },
    {
      "x": 464,
      "z": 175,
      "header": "MAP_MOUNT_MORTAR_1F_ENTRANCE",
      "anchor": 1,
      "y": 0
    },
    {
      "x": 466,
      "z": 164,
      "header": "MAP_MOUNT_MORTAR_1F_ENTRANCE",
      "anchor": 2,
      "y": 0
    },
    {
      "x": 493,
      "z": 171,
      "header": "MAP_MOUNT_MORTAR_1F_ENTRANCE",
      "anchor": 3,
      "y": 0
    }
  ],
  "coords": [
    {
      "scriptId": "_EV_scr_seq_R42_000 + 1",
      "x": 434,
      "z": 172,
      "w": 1,
      "h": 5,
      "y": 0,
      "val": 0,
      "var": "VAR_UNK_4091"
    },
    {
      "scriptId": "_EV_scr_seq_R42_001 + 1",
      "x": 460,
      "z": 181,
      "w": 1,
      "h": 1,
      "y": 0,
      "val": 1,
      "var": "VAR_UNK_4092"
    }
  ]
}