{
  "header": "fielddata/script/scr_seq/event_T23.h",
  "bgs": [
    {
      "scr": "_EV_scr_seq_T23_008 + 1",
      "type": 1,
      "x": 401,
      "y": 460,
      "z": 0,
      "dir": 4
    },
    {
      "scr": "_EV_scr_seq_T23_009 + 1",
      "type": 1,
      "x": 409,
      "y": 471,
      "z": 0,
      "dir": 4
    },
    {
      "scr": "_EV_scr_seq_T23_010 + 1",
      "type": 1,
      "x": 417,
      "y": 468,
      "z": 0,
      "dir": 4
    },
    {
      "scr": "_EV_scr_seq_T23_011 + 1",
      "type": 1,
      "x": 416,
      "y": 461,
      "z": 0,
      "dir": 4
    },
    {
      "scr": "_EV_scr_seq_T23_012 + 1",
      "type": 1,
      "x": 432,
      "y": 461,
      "z": 0,
      "dir": 4
    },
    {
      "scr": "_EV_scr_seq_T23_013 + 1",
      "type": 1,
      "x": 394,
      "y": 461,
      "z": 0,
      "dir": 4
    },
    {
      "scr": "std_hiddenitem_t23_full_heal",
      "type": 2,
      "x": 421,
      "y": 469,
      "z": 0,
      "dir": 4
    }
  ],
  "objects": [
    {
      "id": "obj_T23_rocketm",
      "ovid": "SPRITE_ROCKETM",
      "mvt": 15,
      "type": 0,
      "flag": "FLAG_UNK_19F",
      "scr": "_EV_scr_seq_T23_000 + 1",
      "dirn": 1,
      "eye": 0,
      "unk10": 0,
      "tsure_poke_color": 0,
      "xrange": 0,
      "yrange": 0,
      "x": 434,
      "y": 461,
      "z": 0
    },
    {
      "id": "obj_T23_rocketm_2",
      "ovid": "SPRITE_ROCKETM",
      "mvt": 15,
      "type": 0,
      "flag": "FLAG_UNK_1A9",
      "scr": "_EV_scr_seq_T23_014 + 1",
      "dirn": 1,
      "eye": 0,
      "unk10": 0,
      "tsure_poke_color": 0,
      "xrange": 0,
      "yrange": 0,
      "x": 405,
      "y": 472,
      "z": 0
    },
    {
      "id": "obj_T23_gsoldman1",
      "ovid": "SPRITE_GSOLDMAN1",
      "mvt": 3,
      "type": 0,
      "flag": "FLAG_NOTHING",
      "scr": "_EV_scr_seq_T23_007 + 1",
      "dirn": 3,
      "eye": 0,
      "unk10": 0,
      "tsure_poke_color": 0,
      "xrange": 1,
      "yrange": 1,
      "x": 419,
      "y": 460,
      "z": 0
    },
    {
      "id": "obj_T23_gswoman1",
      "ovid": "SPRITE_GSWOMAN1",
      "mvt": 4,
      "type": 0,
      "flag": "FLAG_NOTHING",
      "scr": "_EV_scr_seq_T23_015 + 1",
      "dirn": 0,
      "eye": 0,
      "unk10": 0,
      "tsure_poke_color": 0,
      "xrange": 0,
      "yrange": 2,
      "x": 411,
      "y": 468,
      "z": 0
    },
    {
      "id": "obj_T23_gsman1",
      "ovid": "SPRITE_GSMAN1",
      "mvt": 5,
      "type": 0,
      "flag": "FLAG_NOTHING",
      "scr": "_EV_scr_seq_T23_016 + 1",
      "dirn": 2,
      "eye": 0,
      "unk10": 0,
      "tsure_poke_color": 0,
      "xrange": 1,
      "yrange": 0,
      "x": 397,
      "y": 461,
      "z": 0
    },
    {
      "id": "obj_T23_tsure_poke_static_slowpoke",
      "ovid": "SPRITE_FOLLOWER_MON_STATIC_SLOWPOKE",
      "mvt": 15,
      "type": 0,
      "flag": "FLAG_HIDE_AZALEA_SLOWPOKES",
      "scr": "_EV_scr_seq_T23_001 + 1",
      "dirn": 1,
      "eye": 0,
      "unk10": 0,
      "tsure_poke_color": 0,
      "xrange": 0,
      "yrange": 0,
      "x": 431,
      "y": 461,
      "z": 0
    },
    {
      "id": "obj_T23_tsure_poke_static_slowpoke_2",
      "ovid": "SPRITE_FOLLOWER_MON_STATIC_SLOWPOKE",
      "mvt": 14,
      "type": 0,
      "flag": "FLAG_HIDE_AZALEA_SLOWPOKES",
      "scr": "_EV_scr_seq_T23_001 + 1",
      "dirn": 0,
      "eye": 0,
      "unk10": 0,
      "tsure_poke_color": 0,
      "xrange": 0,
      "yrange": 0,
      "x": 414,
      "y": 461,
      "z": 0
    },
    {
      "id": "obj_T23_tsure_poke_static_slowpoke_3",
      "ovid": "SPRITE_FOLLOWER_MON_STATIC_SLOWPOKE",
      "mvt": 17,
      "type": 0,
      "flag": "FLAG_HIDE_AZALEA_SLOWPOKES",
      "scr": "_EV_scr_seq_T23_001 + 1",
      "dirn": 3,
      "eye": 0,
      "unk10": 0,
      "tsure_poke_color": 0,
      "xrange": 0,
      "yrange": 0,
      "x": 411,
      "y": 472,
      "z": 0
    },
    {
      "id": "obj_T23_tsure_poke_static_slowpoke_4",
      "ovid": "SPRITE_FOLLOWER_MON_STATIC_SLOWPOKE",
      "mvt": 15,
      "type": 0,
      "flag": "FLAG_HIDE_AZALEA_SLOWPOKES",
      "scr": "_EV_scr_seq_T23_001 + 1",
      "dirn": 1,
      "eye": 0,
      "unk10": 0,
      "tsure_poke_color": 0,
      "xrange": 0,
      "yrange": 0,
      "x": 397,
      "y": 474,
      "z": 0
    },
    {
      "id": "obj_T23_gsrivel",
      "ovid": "SPRITE_GSRIVEL",
      "mvt": 0,
      "type": 0,
      "flag": "FLAG_NOTHING",
      "scr": 0,
      "dirn": 0,
      "eye": 0,
      "unk10": 0,
      "tsure_poke_color": 0,
      "xrange": 0,
      "yrange": 0,
      "x": 384,
      "y": 448,
      "z": 0
    },
    {
      "id": "obj_T23_bonguri",
      "ovid": "SPRITE_BONGURI",
      "mvt": 0,
      "type": 0,
      "flag": "FLAG_NOTHING",
      "scr": "std_apricorn_tree",
      "dirn": 0,
      "eye": 30,
      "unk10": 0,
      "tsure_poke_color": 0,
      "xrange": 0,
      "yrange": 0,
      "x": 396,
      "y": 453,
      "z": 0
    },
    {
      "id": "obj_T23_gsmiddleman1",
      "ovid": "SPRITE_GSMIDDLEMAN1",
      "mvt": 5,
      "type": 0,
      "flag": "FLAG_NOTHING",
      "scr": "_EV_scr_seq_T23_006 + 1",
      "dirn": 3,
      "eye": 0,
      "unk10": 0,
      "tsure_poke_color": 0,
      "xrange": 1,
      "yrange": 0,
      "x": 407,
      "y": 464,
      "z": 0
    },
    {
      "id": "obj_T23_rocketm_3",
      "ovid": "SPRITE_ROCKETM",
      "mvt": 16,
      "type": 0,
      "flag": "FLAG_AZALEA_ROCKET_HARASSING_CIVILIAN",
      "scr": "_EV_scr_seq_T23_005 + 1",
      "dirn": 2,
      "eye": 0,
      "unk10": 0,
      "tsure_poke_color": 0,
      "xrange": 0,
      "yrange": 0,
      "x": 434,
      "y": 463,
      "z": 0
    },
    {
      "id": "obj_T23_gsmiddleman1_2",
      "ovid": "SPRITE_GSMIDDLEMAN1",
      "mvt": 17,
      "type": 0,
      "flag": "FLAG_AZALEA_HARASSED_CIVILIAN",
      "scr": 0,
      "dirn": 3,
      "eye": 0,
      "unk10": 0,
      "tsure_poke_color": 0,
      "xrange": 0,
      "yrange": 0,
      "x": 433,
      "y": 463,
      "z": 0
    }
  ],
  "warps": [
    {
      "x": 392,
      "y": 462,
      "header": "MAP_T23R0101",
      "anchor": 0,
      "height": 0
    },
    {
      "x": 392,
      "y": 463,
      "header": "MAP_T23R0101",
      "anchor": 0,
      "height": 0
    },
    {
      "x": 405,
      "y": 471,
      "header": "MAP_T23GYM0101",
      "anchor": 0,
      "height": 0
    },
    {
      "x": 410,
      "y": 460,
      "header": "MAP_T23PC0101",
      "anchor": 0,
      "height": 0
    },
    {
      "x": 419,
      "y": 468,
      "header": "MAP_T23R0201",
      "anchor": 0,
      "height": 0
    },
    {
      "x": 419,
      "y": 457,
      "header": "MAP_T23FS0101",
      "anchor": 0,
      "height": 0
    },
    {
      "x": 399,
      "y": 454,
      "header": "MAP_T23R0501",
      "anchor": 0,
      "height": 0
    },
    {
      "x": 433,
      "y": 454,
      "header": "MAP_D26R0101",
      "anchor": 0,
      "height": 0
    }
  ],
  "coords": [
    {
      "scr": "_EV_scr_seq_T23_002 + 1",
      "x": 395,
      "y": 462,
      "w": 1,
      "h": 5,
      "z": 0,
      "val": 1,
      "var": "VAR_UNK_4075"
    },
    {
      "scr": "_EV_scr_seq_T23_003 + 1",
      "x": 434,
      "y": 466,
      "w": 1,
      "h": 1,
      "z": 0,
      "val": 0,
      "var": "VAR_UNK_4080"
    }
  ]
}