{
  "header": "fielddata/script/scr_seq/event_R34R0201.h",
  "objects": [
    {
      "id": "obj_R34R0201_gsgirl1",
      "ovid": "SPRITE_GSGIRL1",
      "mvt": 4,
      "type": 0,
      "flag": "FLAG_NOTHING",
      "scr": "_EV_scr_seq_R34R0201_002 + 1",
      "dirn": 1,
      "eye": 0,
      "unk10": 0,
      "tsure_poke_color": 0,
      "xrange": 0,
      "yrange": 2,
      "x": 4,
      "y": 7,
      "z": 0
    },
    {
      "id": "obj_R34R0201_gswoman1",
      "ovid": "SPRITE_GSWOMAN1",
      "mvt": 16,
      "type": 0,
      "flag": "FLAG_NOTHING",
      "scr": "_EV_scr_seq_R34R0201_000 + 1",
      "dirn": 2,
      "eye": 0,
      "unk10": 0,
      "tsure_poke_color": 0,
      "xrange": 0,
      "yrange": 0,
      "x": 9,
      "y": 7,
      "z": 0
    },
    {
      "id": "obj_R34R0201_tsure_poke_static_butterfree",
      "ovid": "SPRITE_FOLLOWER_MON_STATIC_BUTTERFREE",
      "mvt": 16,
      "type": 0,
      "flag": "FLAG_NOTHING",
      "scr": "_EV_scr_seq_R34R0201_001 + 1",
      "dirn": 2,
      "eye": 0,
      "unk10": 0,
      "tsure_poke_color": 0,
      "xrange": 0,
      "yrange": 0,
      "x": 9,
      "y": 8,
      "z": 0
    }
  ],
  "warps": [
    {
      "x": 5,
      "y": 2,
      "header": "MAP_R34",
      "anchor": 0,
      "height": 0
    },
    {
      "x": 5,
      "y": 12,
      "header": "MAP_D36R0101",
      "anchor": 2,
      "height": 0
    }
  ]
}