{
  "header": "fielddata/script/scr_seq/event_D24R0214.h",
  "bgs": [
    {
      "scriptId": "_EV_scr_seq_D24R0214_001 + 1",
      "type": 0,
      "x": 4,
      "z": 4,
      "y": 0,
      "dir": 4
    },
    {
      "scriptId": "_EV_scr_seq_D24R0214_001 + 1",
      "type": 0,
      "x": 8,
      "z": 4,
      "y": 0,
      "dir": 4
    },
    {
      "scriptId": "_EV_scr_seq_D24R0214_001 + 1",
      "type": 0,
      "x": 4,
      "z": 3,
      "y": 0,
      "dir": 4
    },
    {
      "scriptId": "_EV_scr_seq_D24R0214_001 + 1",
      "type": 0,
      "x": 8,
      "z": 3,
      "y": 0,
      "dir": 4
    }
  ],
  "objects": [
    {
      "id": "obj_D24R0214_monstarball",
      "spriteId": "SPRITE_MONSTARBALL",
      "movement": 0,
      "type": 0,
      "eventFlag": "FLAG_HIDE_ITEMBALL_D24R0214_REVIVAL_HERB",
      "scriptId": "std_itemball_d24r0214_revival_herb",
      "facingDirection": 0,
      "param0": 0,
      "param1": 0,
      "param2": 0,
      "xRange": 0,
      "yRange": 0,
      "x": 4,
      "z": 8,
      "y": 0
    },
    {
      "id": "obj_D24R0214_monstarball_2",
      "spriteId": "SPRITE_MONSTARBALL",
      "movement": 0,
      "type": 0,
      "eventFlag": "FLAG_HIDE_ITEMBALL_D24R0214_CHARCOAL",
      "scriptId": "std_itemball_d24r0214_charcoal",
      "facingDirection": 0,
      "param0": 0,
      "param1": 0,
      "param2": 0,
      "xRange": 0,
      "yRange": 0,
      "x": 8,
      "z": 8,
      "y": 0
    },
    {
      "id": "obj_D24R0214_monstarball_3",
      "spriteId": "SPRITE_MONSTARBALL",
      "movement": 0,
      "type": 0,
      "eventFlag": "FLAG_HIDE_ITEMBALL_D24R0214_LIFE_ORB",
      "scriptId": "std_itemball_d24r0214_life_orb",
      "facingDirection": 0,
      "param0": 0,
      "param1": 0,
      "param2": 0,
      "xRange": 0,
      "yRange": 0,
      "x": 4,
      "z": 12,
      "y": 0
    },
    {
      "id": "obj_D24R0214_monstarball_4",
      "spriteId": "SPRITE_MONSTARBALL",
      "movement": 0,
      "type": 0,
      "eventFlag": "FLAG_HIDE_ITEMBALL_D24R0214_LEPPA_BERRY",
      "scriptId": "std_itemball_d24r0214_leppa_berry",
      "facingDirection": 0,
      "param0": 0,
      "param1": 0,
      "param2": 0,
      "xRange": 0,
      "yRange": 0,
      "x": 8,
      "z": 12,
      "y": 0
    }
  ],
  "warps": [
    {
      "x": 6,
      "z": 17,
      "header": "MAP_RUINS_OF_ALPH_NORTHWEST_ENTRANCE_FIRST_ROOM",
      "anchor": 1,
      "y": 0
    }
  ],
  "coords": [
    {
      "scriptId": "_EV_scr_seq_D24R0214_000 + 1",
      "x": 6,
      "z": 3,
      "w": 1,
      "h": 1,
      "y": 0,
      "val": 0,
      "var": "VAR_UNK_40D7"
    }
  ]
}