{
  "bgs": [
    {
      "scr": 1,
      "type": 0,
      "x": 2,
      "y": 13,
      "z": 0,
      "dir": 4
    },
    {
      "scr": 2,
      "type": 0,
      "x": 4,
      "y": 13,
      "z": 0,
      "dir": 4
    },
    {
      "scr": 3,
      "type": 0,
      "x": 6,
      "y": 13,
      "z": 0,
      "dir": 4
    },
    {
      "scr": 4,
      "type": 0,
      "x": 8,
      "y": 13,
      "z": 0,
      "dir": 4
    },
    {
      "scr": 5,
      "type": 0,
      "x": 10,
      "y": 13,
      "z": 0,
      "dir": 4
    },
    {
      "scr": 6,
      "type": 0,
      "x": 2,
      "y": 15,
      "z": 0,
      "dir": 4
    },
    {
      "scr": 7,
      "type": 0,
      "x": 4,
      "y": 15,
      "z": 0,
      "dir": 4
    },
    {
      "scr": 8,
      "type": 0,
      "x": 6,
      "y": 15,
      "z": 0,
      "dir": 4
    },
    {
      "scr": 9,
      "type": 0,
      "x": 8,
      "y": 15,
      "z": 0,
      "dir": 4
    },
    {
      "scr": 10,
      "type": 0,
      "x": 10,
      "y": 15,
      "z": 0,
      "dir": 4
    },
    {
      "scr": 11,
      "type": 0,
      "x": 2,
      "y": 17,
      "z": 0,
      "dir": 4
    },
    {
      "scr": 12,
      "type": 0,
      "x": 4,
      "y": 17,
      "z": 0,
      "dir": 4
    },
    {
      "scr": 13,
      "type": 0,
      "x": 6,
      "y": 17,
      "z": 0,
      "dir": 4
    },
    {
      "scr": 14,
      "type": 0,
      "x": 8,
      "y": 17,
      "z": 0,
      "dir": 4
    },
    {
      "scr": 15,
      "type": 0,
      "x": 10,
      "y": 17,
      "z": 0,
      "dir": 4
    },
    {
      "scr": 26,
      "type": 0,
      "x": 4,
      "y": 20,
      "z": 0,
      "dir": 0
    },
    {
      "scr": 26,
      "type": 0,
      "x": 8,
      "y": 20,
      "z": 0,
      "dir": 0
    }
  ],
  "objects": [
    {
      "id": 0,
      "ovid": 349,
      "mvt": 0,
      "type": 0,
      "flag": "FLAG_UNK_31A",
      "scr": 16,
      "dirn": 0,
      "eye": 0,
      "unk10": 0,
      "unk12": 0,
      "xrange": 0,
      "yrange": 0,
      "x": 5,
      "y": 8,
      "z": 0,
      "unk1E": 0
    },
    {
      "id": 1,
      "ovid": 349,
      "mvt": 0,
      "type": 0,
      "flag": "FLAG_UNK_31A",
      "scr": 17,
      "dirn": 0,
      "eye": 0,
      "unk10": 0,
      "unk12": 0,
      "xrange": 0,
      "yrange": 0,
      "x": 6,
      "y": 8,
      "z": 0,
      "unk1E": 0
    },
    {
      "id": 2,
      "ovid": 349,
      "mvt": 0,
      "type": 0,
      "flag": "FLAG_UNK_31A",
      "scr": 18,
      "dirn": 0,
      "eye": 0,
      "unk10": 0,
      "unk12": 0,
      "xrange": 0,
      "yrange": 0,
      "x": 7,
      "y": 8,
      "z": 0,
      "unk1E": 0
    },
    {
      "id": 3,
      "ovid": 349,
      "mvt": 0,
      "type": 0,
      "flag": "FLAG_UNK_31A",
      "scr": 19,
      "dirn": 0,
      "eye": 0,
      "unk10": 0,
      "unk12": 0,
      "xrange": 0,
      "yrange": 0,
      "x": 5,
      "y": 10,
      "z": 0,
      "unk1E": 0
    },
    {
      "id": 4,
      "ovid": 349,
      "mvt": 0,
      "type": 0,
      "flag": "FLAG_UNK_31A",
      "scr": 20,
      "dirn": 0,
      "eye": 0,
      "unk10": 0,
      "unk12": 0,
      "xrange": 0,
      "yrange": 0,
      "x": 6,
      "y": 10,
      "z": 0,
      "unk1E": 0
    },
    {
      "id": 5,
      "ovid": 349,
      "mvt": 0,
      "type": 0,
      "flag": "FLAG_UNK_31A",
      "scr": 21,
      "dirn": 0,
      "eye": 0,
      "unk10": 0,
      "unk12": 0,
      "xrange": 0,
      "yrange": 0,
      "x": 7,
      "y": 10,
      "z": 0,
      "unk1E": 0
    },
    {
      "id": 6,
      "ovid": 323,
      "mvt": 15,
      "type": 1,
      "flag": "FLAG_NOTHING",
      "scr": 3231,
      "dirn": 1,
      "eye": 3,
      "unk10": 0,
      "unk12": 0,
      "xrange": 0,
      "yrange": 0,
      "x": 5,
      "y": 13,
      "z": 0,
      "unk1E": 0
    },
    {
      "id": 7,
      "ovid": 378,
      "mvt": 17,
      "type": 1,
      "flag": "FLAG_NOTHING",
      "scr": 3395,
      "dirn": 3,
      "eye": 2,
      "unk10": 0,
      "unk12": 0,
      "xrange": 0,
      "yrange": 0,
      "x": 3,
      "y": 16,
      "z": 0,
      "unk1E": 0
    },
    {
      "id": 8,
      "ovid": 341,
      "mvt": 16,
      "type": 1,
      "flag": "FLAG_NOTHING",
      "scr": 3336,
      "dirn": 2,
      "eye": 5,
      "unk10": 0,
      "unk12": 0,
      "xrange": 0,
      "yrange": 0,
      "x": 10,
      "y": 14,
      "z": 0,
      "unk1E": 0
    },
    {
      "id": 9,
      "ovid": 368,
      "mvt": 15,
      "type": 0,
      "flag": "FLAG_UNK_2F0",
      "scr": 24,
      "dirn": 1,
      "eye": 0,
      "unk10": 0,
      "unk12": 0,
      "xrange": 0,
      "yrange": 0,
      "x": 6,
      "y": 4,
      "z": 0,
      "unk1E": 0
    },
    {
      "id": 10,
      "ovid": 168,
      "mvt": 15,
      "type": 0,
      "flag": "FLAG_NOTHING",
      "scr": 25,
      "dirn": 1,
      "eye": 0,
      "unk10": 0,
      "unk12": 0,
      "xrange": 0,
      "yrange": 0,
      "x": 9,
      "y": 20,
      "z": 0,
      "unk1E": 0
    }
  ],
  "warps": [
    {
      "x": 6,
      "y": 22,
      "header": "MAP_T06",
      "anchor": 6,
      "height": 0
    }
  ]
}