{
  "header": "fielddata/script/scr_seq/event_D02R0104.h",
  "bgs": [
    {
      "scr": "_EV_scr_seq_D02R0104_001 + 1",
      "type": 1,
      "x": 22,
      "y": 10,
      "z": 0,
      "dir": 4
    },
    {
      "scr": "std_hiddenitem_d02r0103_max_revive",
      "type": 2,
      "x": 36,
      "y": 2,
      "z": 0,
      "dir": 4
    },
    {
      "scr": "_EV_scr_seq_D02R0104_004 + 1",
      "type": 0,
      "x": 18,
      "y": 10,
      "z": 0,
      "dir": 4
    }
  ],
  "objects": [
    {
      "id": "obj_D02R0104_tsure_poke_static_clefairy",
      "ovid": "SPRITE_FOLLOWER_MON_STATIC_CLEFAIRY",
      "mvt": 14,
      "type": 0,
      "flag": "FLAG_UNK_26E",
      "scr": 0,
      "dirn": 0,
      "eye": 0,
      "unk10": 0,
      "tsure_poke_color": 0,
      "xrange": 0,
      "yrange": 0,
      "x": 9,
      "y": 12,
      "z": 0
    },
    {
      "id": "obj_D02R0104_tsure_poke_static_clefairy_2",
      "ovid": "SPRITE_FOLLOWER_MON_STATIC_CLEFAIRY",
      "mvt": 16,
      "type": 0,
      "flag": "FLAG_UNK_26E",
      "scr": 0,
      "dirn": 2,
      "eye": 0,
      "unk10": 0,
      "tsure_poke_color": 0,
      "xrange": 0,
      "yrange": 0,
      "x": 12,
      "y": 9,
      "z": 0
    },
    {
      "id": "obj_D02R0104_tsure_poke_static_clefairy_3",
      "ovid": "SPRITE_FOLLOWER_MON_STATIC_CLEFAIRY",
      "mvt": 15,
      "type": 0,
      "flag": "FLAG_UNK_26E",
      "scr": 0,
      "dirn": 1,
      "eye": 0,
      "unk10": 0,
      "tsure_poke_color": 0,
      "xrange": 0,
      "yrange": 0,
      "x": 9,
      "y": 6,
      "z": 0
    },
    {
      "id": "obj_D02R0104_tsure_poke_static_clefairy_4",
      "ovid": "SPRITE_FOLLOWER_MON_STATIC_CLEFAIRY",
      "mvt": 17,
      "type": 0,
      "flag": "FLAG_UNK_26E",
      "scr": 0,
      "dirn": 3,
      "eye": 0,
      "unk10": 0,
      "tsure_poke_color": 0,
      "xrange": 0,
      "yrange": 0,
      "x": 6,
      "y": 9,
      "z": 0
    },
    {
      "id": "obj_D02R0104_tsure_poke_static_clefairy_5",
      "ovid": "SPRITE_FOLLOWER_MON_STATIC_CLEFAIRY",
      "mvt": 16,
      "type": 0,
      "flag": "FLAG_UNK_26E",
      "scr": 0,
      "dirn": 2,
      "eye": 0,
      "unk10": 0,
      "tsure_poke_color": 0,
      "xrange": 0,
      "yrange": 0,
      "x": 14,
      "y": 9,
      "z": 0
    },
    {
      "id": "obj_D02R0104_tsure_poke_static_clefairy_6",
      "ovid": "SPRITE_FOLLOWER_MON_STATIC_CLEFAIRY",
      "mvt": 17,
      "type": 0,
      "flag": "FLAG_UNK_26E",
      "scr": 0,
      "dirn": 3,
      "eye": 0,
      "unk10": 0,
      "tsure_poke_color": 0,
      "xrange": 0,
      "yrange": 0,
      "x": 4,
      "y": 9,
      "z": 0
    },
    {
      "id": "obj_D02R0104_monstarball",
      "ovid": "SPRITE_MONSTARBALL",
      "mvt": 0,
      "type": 0,
      "flag": "FLAG_UNK_298",
      "scr": "_EV_scr_seq_D02R0104_003 + 1",
      "dirn": 0,
      "eye": 0,
      "unk10": 0,
      "tsure_poke_color": 0,
      "xrange": 0,
      "yrange": 0,
      "x": 11,
      "y": 12,
      "z": 0
    }
  ],
  "warps": [
    {
      "x": 28,
      "y": 8,
      "header": "MAP_D02R0102",
      "anchor": 1,
      "height": 0
    },
    {
      "x": 32,
      "y": 20,
      "header": "MAP_D02R0102",
      "anchor": 2,
      "height": 0
    }
  ],
  "coords": [
    {
      "scr": "_EV_scr_seq_D02R0104_002 + 1",
      "x": 8,
      "y": 16,
      "w": 3,
      "h": 1,
      "z": 0,
      "val": 0,
      "var": "VAR_UNK_40F6"
    }
  ]
}